[
  {
    "title": "2025 款戴尔 Dell Pro Tower 台式机上架，它在硬件配置上有哪些令人瞩目的升级亮 …",
    "url": "https://www.zhihu.com/question/1911840945453901713",
    "snippet": "Tower Plus EBT2250 凭借其快速的图形性能、合理的中端价格以及同级别产品中出色的配置和扩展性，在很大程度上实现了这一目标。 鉴于其在中等预算用户群 …"
  },
  {
    "title": "明道、teambition、Tower.im、Worktile、trello哪个好？",
    "url": "https://www.zhihu.com/question/25025836",
    "snippet": "本人是一家互联网企业IT人员，前段时间刚好给公司选型团队协作工具，当时测试了很多国内国外的协作软件。国外的 Trello，Asana用起来还可以，但是因为价格 …"
  },
  {
    "title": "T1 CEO 爆料 Faker 在韩国拥有「Faker tower」大厦所有权，这栋楼值多少钱？",
    "url": "https://www.zhihu.com/tardis/bd/ans/2428430680",
    "snippet": "而在拿到LCK春季赛冠军之后，T1老板JOE（就是那个提议打MSC的），闲来无事。 在和LCS名宿大师兄Doublelift等人连线的时候，独家曝料说：“ …"
  },
  {
    "title": "哪个团队协作工具好？明道，teambition，tower？ - 知乎",
    "url": "https://www.zhihu.com/question/28698086",
    "snippet": "哪个团队协作工具好？ 明道，teambition，tower？ 初创移动互联企业评测团队协作工具，主要两个团队：移动办公的销售团队占大多数，主要协作包括销售管道管 …"
  },
  {
    "title": "请问各位，在日本的房屋中 Tower Mansion （高层公寓 或 塔式公寓）到底怎么样？ - 知乎",
    "url": "https://www.zhihu.com/question/269379234",
    "snippet": "请问各位，在日本的房屋中 Tower Mansion （高层公寓 或 塔式公寓）到底怎么样？ 请问各位，在日本的房屋中 Tower Mansion （高层公寓 或 塔式公寓）从 …"
  }
]