[
  {
    "title": "scanner文件夹可以删除吗 - 百度知道",
    "url": "https://zhidao.baidu.com/question/1376220860934420459.html",
    "snippet": "Nov 19, 2022 · scanner文件夹可以删除吗可以删除。scanner是CamScanner 扫描全能王文件夹，可以删除。CamScanner 扫描全能王不是系统文件，用于扫 …"
  },
  {
    "title": "已经连接了打印机怎么添加扫描仪_百度知道",
    "url": "https://zhidao.baidu.com/question/147983144242469485.html",
    "snippet": "Dec 7, 2024 · 已经连接了打印机怎么添加扫描仪要添加扫描仪，请按照以下步骤操作：1. 确保扫描仪已正确连接到计算机，并且已打开电源。如果是USB连接， …"
  },
  {
    "title": "java中Scanner s = new Scanner (System.in);分别是什么意思",
    "url": "https://jingyan.baidu.com/article/f006222818dfe2bad2f0c841.html",
    "snippet": "Scanner是一个类，nextDouble ()是Scanner的成员函数，System.in作为参数传递给Scanner的构造函数，使Scanner用键盘作为输入，然后用new在内存 …"
  },
  {
    "title": "hp打印机显示scanner error是什么问题？_百度知道",
    "url": "https://zhidao.baidu.com/question/571976796780980924.html",
    "snippet": "Apr 11, 2024 · hp打印机显示scanner error是什么问题？机器检测到扫描器出现错误（可能是扫描器卡住、扫描电机故障、扫描灯故障等异常）。一、重启机器。 …"
  },
  {
    "title": "kodak i1220 scanner驱动下载 - 百度知道",
    "url": "https://zhidao.baidu.com/question/1460138564654315820.html",
    "snippet": "May 21, 2025 · kodak i1220 scanner驱动下载Kodak i1220扫描仪驱动下载方式如下：访问柯达官方支持页面：打开浏览器，访问柯达官方文档成像支持 …"
  },
  {
    "title": "Post-Meeting Follow-Through | The Meeting Master's Playbook",
    "url": "https://mutedeck.com/meeting-masters-playbook/post-meeting-follow-through",
    "snippet": "Meeting recaps transform discussions into actionable documentation. They provide clarity, accountability, and a reference point for future …"
  }
]