[
  {
    "title": "Login - access.davidoff.com",
    "url": "https://access.davidoff.com/igcc-us/en_US/USD/my-account/metrics",
    "snippet": "Username Password Forgot password? Sign In Don't have an account? Email support.us@davidoff.com"
  },
  {
    "title": "Forgotten Password - Davidoff Cigars",
    "url": "https://access.davidoff.com/igcc-us/en_US/USD/login/forgot-password",
    "snippet": "Enter the username associated with your account: Enter your username from the original activation email to reset your password. …"
  },
  {
    "title": "Login - Davidoff Cigars",
    "url": "https://access.davidoff.com/igcc-us/en_US/USD/login",
    "snippet": "Username Password Forgot password? Sign In Don't have an account? Email support.us@davidoff.com"
  },
  {
    "title": "Davidoff Store",
    "url": "https://access.davidoff.com/igcc-us/",
    "snippet": "Davidoff Store ... Davidoff Store"
  },
  {
    "title": "Opulent & Mellow Cigars | Cigars by Aroma | Cigar - davidoff.com",
    "url": "http://davidoff.com/cigars/aroma/opulent-mellow",
    "snippet": "Browse Davidoff's opulent and mellow cigars. These cigars are ideal for those who enjoy a soft and rich smoke."
  }
]